ndnt/__init__.py
ndnt/__main__.py
ndnt/arguments.py
ndnt/cli.py
ndnt/extension.py
ndnt/indent.py
ndnt/line.py
ndnt/lines.py
ndnt/ndnt.py
ndnt/paths.py
ndnt/summary.py
ndnt-1.3.1.dist-info/LICENSE
ndnt-1.3.1.dist-info/METADATA
ndnt-1.3.1.dist-info/WHEEL
ndnt-1.3.1.dist-info/entry_points.txt
ndnt-1.3.1.dist-info/top_level.txt
ndnt-1.3.1.dist-info/RECORD
